{
  "formatVersion": 1,
  "database": {
    "version": 1,
    "identityHash": "d7c483b874425a7d4cdcdb8b8f5d02a5",
    "entities": [
      {
        "tableName": "Receipt",
        "createSql": "CREATE TABLE IF NOT EXISTS `${TABLE_NAME}` (`ID` INTEGER PRIMARY KEY AUTOINCREMENT NOT NULL, `ReceiptNo` TEXT NOT NULL, `ReceiptDate` TEXT NOT NULL, `ReceiptIssuer` TEXT NOT NULL, `ReceiptTotal` TEXT NOT NULL, `ReceiptDescription` TEXT NOT NULL, `ReceiptFullText` TEXT NOT NULL)",
        "fields": [
          {
            "fieldPath": "ID",
            "columnName": "ID",
            "affinity": "INTEGER",
            "notNull": true
          },
          {
            "fieldPath": "receiptNo",
            "columnName": "ReceiptNo",
            "affinity": "TEXT",
            "notNull": true
          },
          {
            "fieldPath": "receiptDate",
            "columnName": "ReceiptDate",
            "affinity": "TEXT",
            "notNull": true
          },
          {
            "fieldPath": "receiptIssuer",
            "columnName": "ReceiptIssuer",
            "affinity": "TEXT",
            "notNull": true
          },
          {
            "fieldPath": "receiptTotal",
            "columnName": "ReceiptTotal",
            "affinity": "TEXT",
            "notNull": true
          },
          {
            "fieldPath": "receiptDescription",
            "columnName": "ReceiptDescription",
            "affinity": "TEXT",
            "notNull": true
          },
          {
            "fieldPath": "receiptFullText",
            "columnName": "ReceiptFullText",
            "affinity": "TEXT",
            "notNull": true
          }
        ],
        "primaryKey": {
          "columnNames": [
            "ID"
          ],
          "autoGenerate": true
        },
        "indices": [],
        "foreignKeys": []
      }
    ],
    "setupQueries": [
      "CREATE TABLE IF NOT EXISTS room_master_table (id INTEGER PRIMARY KEY,identity_hash TEXT)",
      "INSERT OR REPLACE INTO room_master_table (id,identity_hash) VALUES(42, \"d7c483b874425a7d4cdcdb8b8f5d02a5\")"
    ]
  }
}